morango/__init__.py
morango/apps.py
morango/errors.py
morango/proquint.py
morango/registry.py
morango/urls.py
morango/utils.py
morango/api/__init__.py
morango/api/fields.py
morango/api/parsers.py
morango/api/permissions.py
morango/api/serializers.py
morango/api/urls.py
morango/api/viewsets.py
morango/constants/__init__.py
morango/constants/api_urls.py
morango/constants/capabilities.py
morango/constants/settings.py
morango/constants/transfer_stages.py
morango/constants/transfer_statuses.py
morango/management/__init__.py
morango/management/commands/__init__.py
morango/management/commands/cleanupsyncs.py
morango/migrations/0001_initial.py
morango/migrations/0001_squashed_0024_auto_20240129_1757.py
morango/migrations/0002_auto_20170511_0400.py
morango/migrations/0002_store_idx_morango_deserialize.py
morango/migrations/0003_auto_20170519_0543.py
morango/migrations/0004_auto_20170520_2112.py
morango/migrations/0005_auto_20170629_2139.py
morango/migrations/0006_instanceidmodel_system_id.py
morango/migrations/0007_auto_20171018_1615.py
morango/migrations/0008_auto_20171114_2217.py
morango/migrations/0009_auto_20171205_0252.py
morango/migrations/0010_auto_20171206_1615.py
morango/migrations/0011_sharedkey.py
morango/migrations/0012_auto_20180927_1658.py
morango/migrations/0013_auto_20190627_1513.py
morango/migrations/0014_syncsession_extra_fields.py
morango/migrations/0015_auto_20200508_2104.py
morango/migrations/0016_store_deserialization_error.py
morango/migrations/0017_store_last_transfer_session_id.py
morango/migrations/0018_auto_20210714_2216.py
morango/migrations/0019_auto_20220113_1807.py
morango/migrations/0020_postgres_fix_nullable.py
morango/migrations/0021_store_partition_index_create.py
morango/migrations/0022_rename_instance_fields.py
morango/migrations/0023_add_instance_id_fields.py
morango/migrations/0024_auto_20240129_1757.py
morango/migrations/__init__.py
morango/models/__init__.py
morango/models/certificates.py
morango/models/core.py
morango-0.8.6.dist-info/licenses/AUTHORS.md
morango-0.8.6.dist-info/licenses/LICENSE
morango-0.8.6.dist-info/METADATA
morango-0.8.6.dist-info/WHEEL
morango-0.8.6.dist-info/top_level.txt
morango-0.8.6.dist-info/RECORD
