Metadata-Version: 2.4
Name: morango
Version: 0.8.6
Summary: Pure Python sqlite-based Django DB replication engine.
Home-page: https://github.com/learningequality/morango
Author: Learning Equality
Author-email: dev@learningequality.org
License: MIT
Keywords: database,syncing,morango
Classifier: Intended Audience :: Developers
Classifier: License :: OSI Approved :: MIT License
Classifier: Natural Language :: English
Classifier: Development Status :: 4 - Beta
Classifier: Programming Language :: Python :: 3.6
Classifier: Programming Language :: Python :: 3.7
Classifier: Programming Language :: Python :: 3.8
Classifier: Programming Language :: Python :: 3.9
Classifier: Programming Language :: Python :: 3.10
Classifier: Programming Language :: Python :: 3.11
Classifier: Programming Language :: Python :: 3.12
Classifier: Programming Language :: Python :: 3.13
Requires-Python: >=3.6,  <3.14
License-File: LICENSE
License-File: AUTHORS.md
Requires-Dist: django<4,>=3
Requires-Dist: django-mptt>0.10.0
Requires-Dist: rsa<4.10
Requires-Dist: djangorestframework>3.10
Requires-Dist: django-ipware==4.0.2
Requires-Dist: requests
Requires-Dist: ifcfg
Dynamic: author
Dynamic: author-email
Dynamic: classifier
Dynamic: description
Dynamic: description-content-type
Dynamic: home-page
Dynamic: keywords
Dynamic: license
Dynamic: license-file
Dynamic: requires-dist
Dynamic: requires-python
Dynamic: summary
